Fazah/__init__.py
Fazah/fazahclass.py
fazah-3.31.dist-info/METADATA
fazah-3.31.dist-info/WHEEL
fazah-3.31.dist-info/top_level.txt
fazah-3.31.dist-info/RECORD
