Metadata-Version: 2.1
Name: fazah
Version: 3.31
Author: Aiden Lang, Will Foster
Author-email: ajlang5@wisc.edu, wjfoster2@wisc.edu
Requires-Dist: deep-translator
Requires-Dist: langdetect
